garmentiq/__init__.py
garmentiq/garment_classes.py
garmentiq/tailor.py
garmentiq/classification/__init__.py
garmentiq/classification/fine_tune_pytorch_nn.py
garmentiq/classification/load_data.py
garmentiq/classification/load_model.py
garmentiq/classification/model_definition.py
garmentiq/classification/predict.py
garmentiq/classification/test_pytorch_nn.py
garmentiq/classification/train_pytorch_nn.py
garmentiq/classification/train_test_split.py
garmentiq/classification/utils.py
garmentiq/instruction/long sleeve dress.json
garmentiq/instruction/long sleeve top.json
garmentiq/instruction/short sleeve dress.json
garmentiq/instruction/short sleeve top.json
garmentiq/instruction/shorts.json
garmentiq/instruction/skirt.json
garmentiq/instruction/trousers.json
garmentiq/instruction/vest dress.json
garmentiq/instruction/vest.json
garmentiq/landmark/__init__.py
garmentiq/landmark/derive.py
garmentiq/landmark/detect.py
garmentiq/landmark/plot.py
garmentiq/landmark/refine.py
garmentiq/landmark/utils.py
garmentiq/landmark/derivation/__init__.py
garmentiq/landmark/derivation/derivation_dict.py
garmentiq/landmark/derivation/derive_keypoint_coord.py
garmentiq/landmark/derivation/line_intersect.py
garmentiq/landmark/derivation/mask_intersect.py
garmentiq/landmark/derivation/prepare_args.py
garmentiq/landmark/derivation/process.py
garmentiq/landmark/derivation/utils.py
garmentiq/landmark/detection/__init__.py
garmentiq/landmark/detection/load_model.py
garmentiq/landmark/detection/model_definition.py
garmentiq/landmark/detection/utils.py
garmentiq/landmark/refinement/__init__.py
garmentiq/landmark/refinement/refine_landmark_with_blur.py
garmentiq/segmentation/__init__.py
garmentiq/segmentation/change_background_color.py
garmentiq/segmentation/extract.py
garmentiq/segmentation/load_model.py
garmentiq/segmentation/plot.py
garmentiq/segmentation/process_and_save_images.py
garmentiq/utils/__init__.py
garmentiq/utils/check_filenames_metadata.py
garmentiq/utils/check_unzipped_dir.py
garmentiq-0.0.4.8.dist-info/licenses/LICENSE
garmentiq-0.0.4.8.dist-info/METADATA
garmentiq-0.0.4.8.dist-info/WHEEL
garmentiq-0.0.4.8.dist-info/top_level.txt
garmentiq-0.0.4.8.dist-info/RECORD
