Metadata-Version: 2.4
Name: garmentiq
Version: 0.0.4.8
Summary: Automated Garment Measurement for Fashion Retail
Author-email: Li Yuan <lyuan@gd.edu.kg>, Xinrui Zhai <zxr86272731@gmail.com>, Fangzhou Ma <fangzhou.ma029@gmail.com>
Maintainer-email: Li Yuan <lyuan@gd.edu.kg>, Xinrui Zhai <zxr86272731@gmail.com>, Fangzhou Ma <fangzhou.ma029@gmail.com>
Project-URL: Homepage, https://garmentiq.ly.gd.edu.kg/
Project-URL: Issues, https://github.com/lygitdata/GarmentIQ/issues
Classifier: Programming Language :: Python :: 3
Classifier: License :: OSI Approved :: MIT License
Requires-Python: >=3.11
License-File: LICENSE
Requires-Dist: tqdm==4.67.1
Requires-Dist: pandas==2.2.2
Requires-Dist: numpy==2.0.0
Requires-Dist: torch==2.7.0
Requires-Dist: torchvision==0.22.0
Requires-Dist: scikit-learn==1.6.1
Requires-Dist: scipy==1.15.2
Requires-Dist: Pillow==11.1.0
Requires-Dist: matplotlib==3.10.0
Requires-Dist: transformers==4.50.3
Requires-Dist: kornia==0.8.0
Requires-Dist: timm==1.0.15
Requires-Dist: einops==0.8.1
Requires-Dist: shapely==2.1.1
Requires-Dist: opencv-python==4.11.0.86
Dynamic: license-file
